{
  "schemaVersion": "1.0.0",
  "generatedAt": "2026-07-18T00:00:00+07:00",
  "records": [
    {
      "id": "demo-feedback:001",
      "case_id": "demo:case:a",
      "facility_id": "fac:bma-hc66",
      "outcome": "RECEIVED_AS_PLANNED",
      "right_accepted": true,
      "service_received": true,
      "unexpected_cost": false,
      "cost_amount": null,
      "missing_documents": [],
      "transferred_to": null,
      "notes": "ข้อมูลตัวอย่างสำหรับการสาธิต ไม่ใช่ประสบการณ์ผู้ใช้จริง",
      "submitted_at": "2026-07-15T10:00:00+07:00",
      "moderation_status": "DEMO_APPROVED",
      "is_demo": true,
      "sample_data_label_th": "ข้อมูลตัวอย่างสำหรับการสาธิต",
      "source_id": "doc:demo:synthetic",
      "effective_from": "2026-07-15",
      "effective_to": null,
      "verification_status": "DEMO_ONLY"
    },
    {
      "id": "demo-feedback:002",
      "case_id": "demo:case:b",
      "facility_id": "fac:bma-hc35",
      "outcome": "RECEIVED_AS_PLANNED",
      "right_accepted": true,
      "service_received": true,
      "unexpected_cost": false,
      "cost_amount": null,
      "missing_documents": [],
      "transferred_to": null,
      "notes": "ข้อมูลตัวอย่างสำหรับการสาธิต ไม่ใช่ประสบการณ์ผู้ใช้จริง",
      "submitted_at": "2026-07-16T11:30:00+07:00",
      "moderation_status": "DEMO_APPROVED",
      "is_demo": true,
      "sample_data_label_th": "ข้อมูลตัวอย่างสำหรับการสาธิต",
      "source_id": "doc:demo:synthetic",
      "effective_from": "2026-07-16",
      "effective_to": null,
      "verification_status": "DEMO_ONLY"
    },
    {
      "id": "demo-feedback:003",
      "case_id": "demo:case:c",
      "facility_id": "fac:sso-1506",
      "outcome": "TRANSFERRED_ELSEWHERE",
      "right_accepted": null,
      "service_received": false,
      "unexpected_cost": null,
      "cost_amount": null,
      "missing_documents": [],
      "transferred_to": "สถานพยาบาลที่เข้าร่วมตามข้อมูลที่ตรวจสอบในวันนั้น",
      "notes": "ข้อมูลตัวอย่างสำหรับการสาธิต: สายด่วนเป็นจุดตรวจสอบสิทธิ ไม่ใช่สถานพยาบาล",
      "submitted_at": "2026-07-17T09:15:00+07:00",
      "moderation_status": "DEMO_APPROVED",
      "is_demo": true,
      "sample_data_label_th": "ข้อมูลตัวอย่างสำหรับการสาธิต",
      "source_id": "doc:demo:synthetic",
      "effective_from": "2026-07-17",
      "effective_to": null,
      "verification_status": "DEMO_ONLY"
    }
  ]
}
